choclo/__init__.py
choclo/_version.py
choclo/constants.py
choclo/utils.py
choclo/dipole/__init__.py
choclo/dipole/_forward.py
choclo/point/__init__.py
choclo/point/_forward.py
choclo/point/_kernels.py
choclo/prism/__init__.py
choclo/prism/_gravity.py
choclo/prism/_kernels.py
choclo/prism/_magnetic.py
choclo/prism/_utils.py
choclo/tests/__init__.py
choclo/tests/test_dipole.py
choclo/tests/test_distance.py
choclo/tests/test_point_gravity.py
choclo/tests/test_prism_gravity.py
choclo/tests/test_prism_kernels.py
choclo/tests/test_prism_magnetic.py
choclo/tests/test_prism_safe_log.py
choclo/tests/utils.py
choclo-0.3.1.dist-info/AUTHORS.md
choclo-0.3.1.dist-info/LICENSE.txt
choclo-0.3.1.dist-info/METADATA
choclo-0.3.1.dist-info/WHEEL
choclo-0.3.1.dist-info/top_level.txt
choclo-0.3.1.dist-info/RECORD
