Metadata-Version: 2.1
Name: choclo
Version: 0.3.1
Summary: Kernel functions for your geophysical models
Author-email: The Choclo Developers <fatiandoaterra@protonmail.com>
Maintainer-email: Santiago Soler <santisoler@fastmail.com>
License: BSD-3-Clause
Project-URL: Documentation, https://www.fatiando.org/choclo
Project-URL: Changelog, https://www.fatiando.org/choclo/latest/changes.html
Project-URL: Bug Tracker, https://github.com/fatiando/choclo/issues
Project-URL: Source Code, https://github.com/fatiando/choclo
Keywords: geoscience,geophysics
Classifier: Development Status :: 5 - Production/Stable
Classifier: Intended Audience :: Science/Research
Classifier: Intended Audience :: Developers
Classifier: Intended Audience :: Education
Classifier: License :: OSI Approved :: BSD License
Classifier: Natural Language :: English
Classifier: Operating System :: OS Independent
Classifier: Programming Language :: Python :: 3
Classifier: Programming Language :: Python :: 3.8
Classifier: Programming Language :: Python :: 3.9
Classifier: Programming Language :: Python :: 3.10
Classifier: Programming Language :: Python :: 3.11
Classifier: Programming Language :: Python :: 3.12
Classifier: Topic :: Scientific/Engineering
Classifier: Topic :: Software Development :: Libraries
Requires-Python: >=3.8
License-File: LICENSE.txt
License-File: AUTHORS.md
Requires-Dist: numpy>=1.19
Requires-Dist: numba>=0.52
